test/__init__.py
test/test_grammar.py
trishula/__init__.py
trishula/decorator.py
trishula/grammar.py
trishula-0.0.9.dist-info/METADATA
trishula-0.0.9.dist-info/WHEEL
trishula-0.0.9.dist-info/top_level.txt
trishula-0.0.9.dist-info/RECORD
