Metadata-Version: 2.1
Name: trishula
Version: 0.0.9
Summary: The modern PEG parser combinator for python
Home-page: https://github.com/minamorl/trishula
Author: minamorl
Author-email: minamorl@minamorl.com
License: UNKNOWN
Platform: UNKNOWN
